{
  "title": "On-Demand KRS Assessment — Frontend Tasks",
  "description": "When a user searches for a KRS number, the UI should check readiness and show a real-time pipeline progress indicator if data needs to be fetched/computed. The backend exposes a job-based API with polling.",
  "api_contract": {
    "start_assessment": {
      "method": "POST",
      "path": "/api/assessment/{krs}",
      "auth": "Bearer JWT + KRS access",
      "response_202": {
        "description": "Pipeline started — poll for progress",
        "body": {
          "job_id": "uuid",
          "krs": "0000012345",
          "status": "pending",
          "stage": null,
          "message": "Assessment pipeline started"
        }
      },
      "response_200": {
        "description": "Data already complete — predictions ready",
        "body": {
          "job_id": null,
          "krs": "0000012345",
          "status": "ready",
          "stage": null,
          "message": "All data available",
          "data_summary": {
            "entity_exists": true,
            "documents_total": 5,
            "documents_downloaded": 5,
            "reports_ingested": 5,
            "features_computed": true,
            "predictions_available": true,
            "latest_fiscal_year": 2024
          }
        }
      },
      "response_404": {
        "description": "KRS not found upstream (entity does not exist in RDF)",
        "body": {
          "detail": "KRS entity not found upstream"
        }
      }
    },
    "poll_job": {
      "method": "GET",
      "path": "/api/assessment/jobs/{job_id}",
      "auth": "Bearer JWT",
      "response_200": {
        "body": {
          "job_id": "uuid",
          "krs": "0000012345",
          "status": "running | completed | failed",
          "stage": "checking_data | discovering_documents | downloading | etl_ingesting | computing_features | scoring",
          "progress": {
            "documents_total": 5,
            "documents_downloaded": 3,
            "documents_ingested": 2,
            "features_computed": false,
            "predictions_scored": false
          },
          "error_message": null,
          "created_at": "2026-04-06T12:00:00Z",
          "updated_at": "2026-04-06T12:00:05Z"
        }
      }
    }
  },
  "tasks": [
    {
      "id": "FE-001",
      "title": "Add KRS search readiness check on search submit",
      "description": "When the user submits a KRS search (existing search bar), call POST /api/assessment/{krs} BEFORE navigating to the predictions page. This single call either returns 200 (data ready, proceed to predictions view) or 202 (pipeline started, show progress UI).",
      "acceptance_criteria": [
        "On search submit, POST to /api/assessment/{krs}",
        "If 200: navigate directly to /predictions/{krs} as today",
        "If 202: show the pipeline progress component (FE-002) with the returned job_id",
        "If 404: show 'KRS not found' inline error in the search bar"
      ]
    },
    {
      "id": "FE-002",
      "title": "Build pipeline progress component",
      "description": "A step-indicator component that shows the user where the backend is in the assessment pipeline. Shows 6 stages as a vertical stepper or horizontal progress bar. Polls GET /api/assessment/jobs/{job_id} every 2 seconds.",
      "stages": [
        {"key": "checking_data", "label": "Sprawdzanie danych w bazie", "label_en": "Checking database"},
        {"key": "discovering_documents", "label": "Wyszukiwanie dokumentow", "label_en": "Discovering documents"},
        {"key": "downloading", "label": "Pobieranie dokumentow", "label_en": "Downloading documents"},
        {"key": "etl_ingesting", "label": "Przetwarzanie sprawozdan", "label_en": "Processing financial statements"},
        {"key": "computing_features", "label": "Obliczanie wskaznikow", "label_en": "Computing financial ratios"},
        {"key": "scoring", "label": "Generowanie prognoz", "label_en": "Generating predictions"}
      ],
      "acceptance_criteria": [
        "Shows all 6 stages with current stage highlighted/animated",
        "Past stages show green checkmark",
        "Current stage shows spinner/pulse animation",
        "Future stages are grayed out",
        "During 'downloading' stage, show document counter (e.g. '3/5 documents downloaded') from progress.documents_downloaded / progress.documents_total",
        "Poll every 2 seconds using setInterval or react-query refetchInterval",
        "Stop polling when status is 'completed' or 'failed'",
        "On 'completed': auto-navigate to /predictions/{krs} after 1s delay",
        "On 'failed': show error_message with a 'Retry' button that re-triggers POST /api/assessment/{krs}"
      ]
    },
    {
      "id": "FE-003",
      "title": "Add loading skeleton to predictions page",
      "description": "If the user navigates directly to /predictions/{krs} (e.g. bookmark) and there's no data, show a CTA to trigger the assessment pipeline instead of just a 404.",
      "acceptance_criteria": [
        "If GET /api/predictions/{krs} returns 404, show a card: 'No predictions available for this company yet. Click to analyze.' with a button",
        "Button triggers POST /api/assessment/{krs} and switches to the pipeline progress component (FE-002)",
        "If predictions exist but are stale (scored_at > 30 days ago), show a subtle 'Refresh data' link that triggers the same flow"
      ]
    },
    {
      "id": "FE-004",
      "title": "Handle concurrent assessment requests gracefully",
      "description": "If a pipeline is already running for a given KRS (another user or tab triggered it), the backend returns 202 with the existing job_id. The frontend should handle this seamlessly.",
      "acceptance_criteria": [
        "If POST /api/assessment/{krs} returns 202 with an already-running job_id, attach to that job's progress (same polling flow)",
        "Show a subtle note: 'Analysis already in progress' so the user knows they didn't trigger a duplicate",
        "If the job was started by another user, this is transparent — same UX"
      ]
    },
    {
      "id": "FE-005",
      "title": "Add assessment status to KRS search results list",
      "description": "When showing search results or the user's KRS access list, indicate which companies have predictions ready vs need processing.",
      "acceptance_criteria": [
        "In the KRS list/dashboard, show a status badge per KRS: 'Ready' (green), 'Processing' (yellow spinner), 'No data' (gray)",
        "Badge state derived from data_summary in the assessment response or from existing predictions data",
        "Clicking a 'No data' badge triggers the assessment flow"
      ]
    }
  ]
}
